convosense_utilities/__init__.py
convosense_utilities/email_signature_remover.py
convosense_utilities-1.0.1.dist-info/LICENSE
convosense_utilities-1.0.1.dist-info/METADATA
convosense_utilities-1.0.1.dist-info/WHEEL
convosense_utilities-1.0.1.dist-info/top_level.txt
convosense_utilities-1.0.1.dist-info/RECORD
