Metadata-Version: 2.1
Name: convosense-utilities
Version: 1.0.1
Summary: A package to extract the email body out of the email text, by removing signature, in order to get accurate sentiment results.
Author-email: Swapnil Bonde <swapnilbonde94@gmail.com>
Project-URL: GitHub repo, https://github.com/convosense/email_signature_remover
Project-URL: Bug Tracker, https://github.com/convosense/email_signature_remover/issues
Classifier: Programming Language :: Python :: 3
Classifier: License :: OSI Approved :: Apache Software License
Classifier: Operating System :: OS Independent
Requires-Python: >=3.7
License-File: LICENSE
Requires-Dist: email-reply-parser
Requires-Dist: nltk
Requires-Dist: spacy
